CHANGELOG
LICENSE
MANIFEST.in
Makefile
README.rst
app.yaml
conf.ini
epydoc.config
setup.py
Muntjac.egg-info/PKG-INFO
Muntjac.egg-info/SOURCES.txt
Muntjac.egg-info/dependency_links.txt
Muntjac.egg-info/entry_points.txt
Muntjac.egg-info/not-zip-safe
Muntjac.egg-info/requires.txt
Muntjac.egg-info/top_level.txt
muntjac/__init__.py
muntjac/api.py
muntjac/application.py
muntjac/main.py
muntjac/messages.py
muntjac/util.py
muntjac/addon/__init__.py
muntjac/addon/canvas/__init__.py
muntjac/addon/canvas/canvas.py
muntjac/addon/canvas/canvas_app.py
muntjac/addon/codemirror/__init__.py
muntjac/addon/codemirror/code_mirror.py
muntjac/addon/codemirror/code_mirror_application.py
muntjac/addon/codemirror/client/__init__.py
muntjac/addon/codemirror/client/code_mode.py
muntjac/addon/codemirror/client/code_theme.py
muntjac/addon/colorpicker/__init__.py
muntjac/addon/colorpicker/color.py
muntjac/addon/colorpicker/color_change_event.py
muntjac/addon/colorpicker/color_picker.py
muntjac/addon/colorpicker/color_picker_application.py
muntjac/addon/colorpicker/color_picker_demo.py
muntjac/addon/colorpicker/color_picker_gradient.py
muntjac/addon/colorpicker/color_picker_grid.py
muntjac/addon/colorpicker/color_picker_history.py
muntjac/addon/colorpicker/color_picker_popup.py
muntjac/addon/colorpicker/color_picker_preview.py
muntjac/addon/colorpicker/color_picker_select.py
muntjac/addon/colorpicker/color_selector.py
muntjac/addon/csstools/__init__.py
muntjac/addon/csstools/render_info.py
muntjac/addon/csstools/render_info_fetcher.py
muntjac/addon/csstools/test_application.py
muntjac/addon/csstools/client/__init__.py
muntjac/addon/csstools/client/v_render_info_fetcher.py
muntjac/addon/google_maps/__init__.py
muntjac/addon/google_maps/google_map.py
muntjac/addon/google_maps/google_map_app.py
muntjac/addon/google_maps/overlay/__init__.py
muntjac/addon/google_maps/overlay/basic_marker.py
muntjac/addon/google_maps/overlay/basic_marker_source.py
muntjac/addon/google_maps/overlay/info_window_tab.py
muntjac/addon/google_maps/overlay/marker.py
muntjac/addon/google_maps/overlay/marker_source.py
muntjac/addon/google_maps/overlay/poly_overlay.py
muntjac/addon/google_maps/overlay/polygon.py
