Metadata-Version: 1.1
Name: Muntjac
Version: 1.1.2
Summary: Web application GUI toolkit
Home-page: http://www.muntiacus.org/
Author: Richard Lincoln
Author-email: r.w.lincoln@gmail.com
License: UNKNOWN
Platform: UNKNOWN
Classifier: Development Status :: 5 - Production/Stable
Classifier: Intended Audience :: Developers
Classifier: License :: OSI Approved :: Apache Software License
Classifier: Programming Language :: Python
Classifier: Topic :: Internet :: WWW/HTTP :: Dynamic Content
Classifier: Topic :: Internet :: WWW/HTTP :: WSGI :: Application
